{"nodes": [{"id": "users_gsoultan_golandprojects_hermod_pkg_comm_source_sap_sap_go", "label": "sap.go", "file_type": "code", "source_file": "pkg/comm/source/sap/sap.go", "source_location": "L1"}, {"id": "sap_sourceconfig", "label": "SourceConfig", "file_type": "code", "source_file": "pkg/comm/source/sap/sap.go", "source_location": "L17"}, {"id": "sap_source", "label": "Source", "file_type": "code", "source_file": "pkg/comm/source/sap/sap.go", "source_location": "L29"}, {"id": "logger", "label": "Logger", "file_type": "code", "source_file": "", "source_location": "", "origin_file": "/Users/gsoultan/GolandProjects/Hermod/pkg/comm/source/sap/sap.go"}, {"id": "client", "label": "Client", "file_type": "code", "source_file": "", "source_location": "", "origin_file": "/Users/gsoultan/GolandProjects/Hermod/pkg/comm/source/sap/sap.go"}, {"id": "mutex", "label": "Mutex", "file_type": "code", "source_file": "", "source_location": "", "origin_file": "/Users/gsoultan/GolandProjects/Hermod/pkg/comm/source/sap/sap.go"}, {"id": "users_gsoultan_golandprojects_hermod_pkg_comm_source_sap_sap_newsource", "label": "NewSource()", "file_type": "code", "source_file": "pkg/comm/source/sap/sap.go", "source_location": "L37"}, {"id": "sap_source_getstate", "label": ".GetState()", "file_type": "code", "source_file": "pkg/comm/source/sap/sap.go", "source_location": "L45"}, {"id": "sap_source_setstate", "label": ".SetState()", "file_type": "code", "source_file": "pkg/comm/source/sap/sap.go", "source_location": "L51"}, {"id": "sap_source_read", "label": ".Read()", "file_type": "code", "source_file": "pkg/comm/source/sap/sap.go", "source_location": "L57"}, {"id": "context", "label": "Context", "file_type": "code", "source_file": "", "source_location": "", "origin_file": "/Users/gsoultan/GolandProjects/Hermod/pkg/comm/source/sap/sap.go"}, {"id": "message", "label": "Message", "file_type": "code", "source_file": "", "source_location": "", "origin_file": "/Users/gsoultan/GolandProjects/Hermod/pkg/comm/source/sap/sap.go"}, {"id": "sap_source_ack", "label": ".Ack()", "file_type": "code", "source_file": "pkg/comm/source/sap/sap.go", "source_location": "L153"}, {"id": "sap_source_ping", "label": ".Ping()", "file_type": "code", "source_file": "pkg/comm/source/sap/sap.go", "source_location": "L157"}, {"id": "sap_source_close", "label": ".Close()", "file_type": "code", "source_file": "pkg/comm/source/sap/sap.go", "source_location": "L174"}, {"id": "sap_source_name", "label": ".Name()", "file_type": "code", "source_file": "pkg/comm/source/sap/sap.go", "source_location": "L178"}], "edges": [{"source": "users_gsoultan_golandprojects_hermod_pkg_comm_source_sap_sap_go", "target": "go_pkg_context", "relation": "imports_from", "confidence": "EXTRACTED", "source_file": "pkg/comm/source/sap/sap.go", "source_location": "L4", "weight": 1.0, "context": "import"}, {"source": "users_gsoultan_golandprojects_hermod_pkg_comm_source_sap_sap_go", "target": "go_pkg_encoding_json", "relation": "imports_from", "confidence": "EXTRACTED", "source_file": "pkg/comm/source/sap/sap.go", "source_location": "L5", "weight": 1.0, "context": "import"}, {"source": "users_gsoultan_golandprojects_hermod_pkg_comm_source_sap_sap_go", "target": "go_pkg_fmt", "relation": "imports_from", "confidence": "EXTRACTED", "source_file": "pkg/comm/source/sap/sap.go", "source_location": "L6", "weight": 1.0, "context": "import"}, {"source": "users_gsoultan_golandprojects_hermod_pkg_comm_source_sap_sap_go", "target": "go_pkg_io", "relation": "imports_from", "confidence": "EXTRACTED", "source_file": "pkg/comm/source/sap/sap.go", "source_location": "L7", "weight": 1.0, "context": "import"}, {"source": "users_gsoultan_golandprojects_hermod_pkg_comm_source_sap_sap_go", "target": "go_pkg_net_http", "relation": "imports_from", "confidence": "EXTRACTED", "source_file": "pkg/comm/source/sap/sap.go", "source_location": "L8", "weight": 1.0, "context": "import"}, {"source": "users_gsoultan_golandprojects_hermod_pkg_comm_source_sap_sap_go", "target": "go_pkg_strings", "relation": "imports_from", "confidence": "EXTRACTED", "source_file": "pkg/comm/source/sap/sap.go", "source_location": "L9", "weight": 1.0, "context": "import"}, {"source": "users_gsoultan_golandprojects_hermod_pkg_comm_source_sap_sap_go", "target": "go_pkg_sync", "relation": "imports_from", "confidence": "EXTRACTED", "source_file": "pkg/comm/source/sap/sap.go", "source_location": "L10", "weight": 1.0, "context": "import"}, {"source": "users_gsoultan_golandprojects_hermod_pkg_comm_source_sap_sap_go", "target": "go_pkg_time", "relation": "imports_from", "confidence": "EXTRACTED", "source_file": "pkg/comm/source/sap/sap.go", "source_location": "L11", "weight": 1.0, "context": "import"}, {"source": "users_gsoultan_golandprojects_hermod_pkg_comm_source_sap_sap_go", "target": "go_pkg_github_com_user_hermod", "relation": "imports_from", "confidence": "EXTRACTED", "source_file": "pkg/comm/source/sap/sap.go", "source_location": "L13", "weight": 1.0, "context": "import"}, {"source": "users_gsoultan_golandprojects_hermod_pkg_comm_source_sap_sap_go", "target": "go_pkg_github_com_user_hermod_pkg_comm_message", "relation": "imports_from", "confidence": "EXTRACTED", "source_file": "pkg/comm/source/sap/sap.go", "source_location": "L14", "weight": 1.0, "context": "import"}, {"source": "users_gsoultan_golandprojects_hermod_pkg_comm_source_sap_sap_go", "target": "sap_sourceconfig", "relation": "contains", "confidence": "EXTRACTED", "source_file": "pkg/comm/source/sap/sap.go", "source_location": "L17", "weight": 1.0}, {"source": "users_gsoultan_golandprojects_hermod_pkg_comm_source_sap_sap_go", "target": "sap_source", "relation": "contains", "confidence": "EXTRACTED", "source_file": "pkg/comm/source/sap/sap.go", "source_location": "L29", "weight": 1.0}, {"source": "sap_source", "target": "sap_sourceconfig", "relation": "references", "confidence": "EXTRACTED", "source_file": "pkg/comm/source/sap/sap.go", "source_location": "L30", "weight": 1.0, "context": "field"}, {"source": "sap_source", "target": "logger", "relation": "references", "confidence": "EXTRACTED", "source_file": "pkg/comm/source/sap/sap.go", "source_location": "L31", "weight": 1.0, "context": "field"}, {"source": "sap_source", "target": "client", "relation": "references", "confidence": "EXTRACTED", "source_file": "pkg/comm/source/sap/sap.go", "source_location": "L32", "weight": 1.0, "context": "field"}, {"source": "sap_source", "target": "mutex", "relation": "references", "confidence": "EXTRACTED", "source_file": "pkg/comm/source/sap/sap.go", "source_location": "L34", "weight": 1.0, "context": "field"}, {"source": "users_gsoultan_golandprojects_hermod_pkg_comm_source_sap_sap_go", "target": "users_gsoultan_golandprojects_hermod_pkg_comm_source_sap_sap_newsource", "relation": "contains", "confidence": "EXTRACTED", "source_file": "pkg/comm/source/sap/sap.go", "source_location": "L37", "weight": 1.0}, {"source": "users_gsoultan_golandprojects_hermod_pkg_comm_source_sap_sap_newsource", "target": "sap_sourceconfig", "relation": "references", "confidence": "EXTRACTED", "source_file": "pkg/comm/source/sap/sap.go", "source_location": "L37", "weight": 1.0, "context": "parameter_type"}, {"source": "users_gsoultan_golandprojects_hermod_pkg_comm_source_sap_sap_newsource", "target": "logger", "relation": "references", "confidence": "EXTRACTED", "source_file": "pkg/comm/source/sap/sap.go", "source_location": "L37", "weight": 1.0, "context": "parameter_type"}, {"source": "users_gsoultan_golandprojects_hermod_pkg_comm_source_sap_sap_newsource", "target": "sap_source", "relation": "references", "confidence": "EXTRACTED", "source_file": "pkg/comm/source/sap/sap.go", "source_location": "L37", "weight": 1.0, "context": "return_type"}, {"source": "sap_source", "target": "sap_source_getstate", "relation": "method", "confidence": "EXTRACTED", "source_file": "pkg/comm/source/sap/sap.go", "source_location": "L45", "weight": 1.0}, {"source": "sap_source", "target": "sap_source_setstate", "relation": "method", "confidence": "EXTRACTED", "source_file": "pkg/comm/source/sap/sap.go", "source_location": "L51", "weight": 1.0}, {"source": "sap_source", "target": "sap_source_read", "relation": "method", "confidence": "EXTRACTED", "source_file": "pkg/comm/source/sap/sap.go", "source_location": "L57", "weight": 1.0}, {"source": "sap_source_read", "target": "context", "relation": "references", "confidence": "EXTRACTED", "source_file": "pkg/comm/source/sap/sap.go", "source_location": "L57", "weight": 1.0, "context": "parameter_type"}, {"source": "sap_source_read", "target": "message", "relation": "references", "confidence": "EXTRACTED", "source_file": "pkg/comm/source/sap/sap.go", "source_location": "L57", "weight": 1.0, "context": "return_type"}, {"source": "sap_source", "target": "sap_source_ack", "relation": "method", "confidence": "EXTRACTED", "source_file": "pkg/comm/source/sap/sap.go", "source_location": "L153", "weight": 1.0}, {"source": "sap_source_ack", "target": "context", "relation": "references", "confidence": "EXTRACTED", "source_file": "pkg/comm/source/sap/sap.go", "source_location": "L153", "weight": 1.0, "context": "parameter_type"}, {"source": "sap_source_ack", "target": "message", "relation": "references", "confidence": "EXTRACTED", "source_file": "pkg/comm/source/sap/sap.go", "source_location": "L153", "weight": 1.0, "context": "parameter_type"}, {"source": "sap_source", "target": "sap_source_ping", "relation": "method", "confidence": "EXTRACTED", "source_file": "pkg/comm/source/sap/sap.go", "source_location": "L157", "weight": 1.0}, {"source": "sap_source_ping", "target": "context", "relation": "references", "confidence": "EXTRACTED", "source_file": "pkg/comm/source/sap/sap.go", "source_location": "L157", "weight": 1.0, "context": "parameter_type"}, {"source": "sap_source", "target": "sap_source_close", "relation": "method", "confidence": "EXTRACTED", "source_file": "pkg/comm/source/sap/sap.go", "source_location": "L174", "weight": 1.0}, {"source": "sap_source", "target": "sap_source_name", "relation": "method", "confidence": "EXTRACTED", "source_file": "pkg/comm/source/sap/sap.go", "source_location": "L178", "weight": 1.0}, {"source": "sap_source_read", "target": "sap_source_close", "relation": "calls", "context": "call", "confidence": "EXTRACTED", "source_file": "pkg/comm/source/sap/sap.go", "source_location": "L111", "weight": 1.0}, {"source": "sap_source_ping", "target": "sap_source_close", "relation": "calls", "context": "call", "confidence": "EXTRACTED", "source_file": "pkg/comm/source/sap/sap.go", "source_location": "L167", "weight": 1.0}], "raw_calls": [{"caller_nid": "sap_source_getstate", "callee": "Lock", "is_member_call": true, "source_file": "pkg/comm/source/sap/sap.go", "source_location": "L46"}, {"caller_nid": "sap_source_getstate", "callee": "Unlock", "is_member_call": true, "source_file": "pkg/comm/source/sap/sap.go", "source_location": "L47"}, {"caller_nid": "sap_source_setstate", "callee": "Lock", "is_member_call": true, "source_file": "pkg/comm/source/sap/sap.go", "source_location": "L52"}, {"caller_nid": "sap_source_setstate", "callee": "Unlock", "is_member_call": true, "source_file": "pkg/comm/source/sap/sap.go", "source_location": "L53"}, {"caller_nid": "sap_source_read", "callee": "Lock", "is_member_call": true, "source_file": "pkg/comm/source/sap/sap.go", "source_location": "L58"}, {"caller_nid": "sap_source_read", "callee": "Unlock", "is_member_call": true, "source_file": "pkg/comm/source/sap/sap.go", "source_location": "L60"}, {"caller_nid": "sap_source_read", "callee": "Sprintf", "is_member_call": false, "source_file": "pkg/comm/source/sap/sap.go", "source_location": "L63"}, {"caller_nid": "sap_source_read", "callee": "Sprintf", "is_member_call": false, "source_file": "pkg/comm/source/sap/sap.go", "source_location": "L68"}, {"caller_nid": "sap_source_read", "callee": "append", "is_member_call": false, "source_file": "pkg/comm/source/sap/sap.go", "source_location": "L70"}, {"caller_nid": "sap_source_read", "callee": "Sprintf", "is_member_call": false, "source_file": "pkg/comm/source/sap/sap.go", "source_location": "L70"}, {"caller_nid": "sap_source_read", "callee": "append", "is_member_call": false, "source_file": "pkg/comm/source/sap/sap.go", "source_location": "L72"}, {"caller_nid": "sap_source_read", "callee": "append", "is_member_call": false, "source_file": "pkg/comm/source/sap/sap.go", "source_location": "L75"}, {"caller_nid": "sap_source_read", "callee": "append", "is_member_call": false, "source_file": "pkg/comm/source/sap/sap.go", "source_location": "L79"}, {"caller_nid": "sap_source_read", "callee": "append", "is_member_call": false, "source_file": "pkg/comm/source/sap/sap.go", "source_location": "L83"}, {"caller_nid": "sap_source_read", "callee": "append", "is_member_call": false, "source_file": "pkg/comm/source/sap/sap.go", "source_location": "L86"}, {"caller_nid": "sap_source_read", "callee": "WriteString", "is_member_call": true, "source_file": "pkg/comm/source/sap/sap.go", "source_location": "L93"}, {"caller_nid": "sap_source_read", "callee": "NewRequestWithContext", "is_member_call": false, "source_file": "pkg/comm/source/sap/sap.go", "source_location": "L98"}, {"caller_nid": "sap_source_read", "callee": "SetBasicAuth", "is_member_call": true, "source_file": "pkg/comm/source/sap/sap.go", "source_location": "L104"}, {"caller_nid": "sap_source_read", "callee": "Do", "is_member_call": true, "source_file": "pkg/comm/source/sap/sap.go", "source_location": "L107"}, {"caller_nid": "sap_source_read", "callee": "ReadAll", "is_member_call": false, "source_file": "pkg/comm/source/sap/sap.go", "source_location": "L114"}, {"caller_nid": "sap_source_read", "callee": "Errorf", "is_member_call": false, "source_file": "pkg/comm/source/sap/sap.go", "source_location": "L115"}, {"caller_nid": "sap_source_read", "callee": "string", "is_member_call": false, "source_file": "pkg/comm/source/sap/sap.go", "source_location": "L115"}, {"caller_nid": "sap_source_read", "callee": "Decode", "is_member_call": true, "source_file": "pkg/comm/source/sap/sap.go", "source_location": "L124"}, {"caller_nid": "sap_source_read", "callee": "NewDecoder", "is_member_call": false, "source_file": "pkg/comm/source/sap/sap.go", "source_location": "L124"}, {"caller_nid": "sap_source_read", "callee": "Lock", "is_member_call": true, "source_file": "pkg/comm/source/sap/sap.go", "source_location": "L138"}, {"caller_nid": "sap_source_read", "callee": "Sprintf", "is_member_call": false, "source_file": "pkg/comm/source/sap/sap.go", "source_location": "L139"}, {"caller_nid": "sap_source_read", "callee": "Unlock", "is_member_call": true, "source_file": "pkg/comm/source/sap/sap.go", "source_location": "L140"}, {"caller_nid": "sap_source_read", "callee": "AcquireMessage", "is_member_call": false, "source_file": "pkg/comm/source/sap/sap.go", "source_location": "L144"}, {"caller_nid": "sap_source_read", "callee": "SetID", "is_member_call": true, "source_file": "pkg/comm/source/sap/sap.go", "source_location": "L145"}, {"caller_nid": "sap_source_read", "callee": "Sprintf", "is_member_call": false, "source_file": "pkg/comm/source/sap/sap.go", "source_location": "L145"}, {"caller_nid": "sap_source_read", "callee": "UnixNano", "is_member_call": true, "source_file": "pkg/comm/source/sap/sap.go", "source_location": "L145"}, {"caller_nid": "sap_source_read", "callee": "Now", "is_member_call": false, "source_file": "pkg/comm/source/sap/sap.go", "source_location": "L145"}, {"caller_nid": "sap_source_read", "callee": "SetData", "is_member_call": true, "source_file": "pkg/comm/source/sap/sap.go", "source_location": "L147"}, {"caller_nid": "sap_source_ping", "callee": "Sprintf", "is_member_call": false, "source_file": "pkg/comm/source/sap/sap.go", "source_location": "L158"}, {"caller_nid": "sap_source_ping", "callee": "NewRequestWithContext", "is_member_call": false, "source_file": "pkg/comm/source/sap/sap.go", "source_location": "L159"}, {"caller_nid": "sap_source_ping", "callee": "SetBasicAuth", "is_member_call": true, "source_file": "pkg/comm/source/sap/sap.go", "source_location": "L161"}, {"caller_nid": "sap_source_ping", "callee": "Do", "is_member_call": true, "source_file": "pkg/comm/source/sap/sap.go", "source_location": "L163"}, {"caller_nid": "sap_source_ping", "callee": "Errorf", "is_member_call": false, "source_file": "pkg/comm/source/sap/sap.go", "source_location": "L169"}]}