{"nodes": [{"id": "users_gsoultan_golandprojects_hermod_pkg_comm_sink_decorators_test_go", "label": "decorators_test.go", "file_type": "code", "source_file": "pkg/comm/sink/decorators_test.go", "source_location": "L1"}, {"id": "sink_mocksink", "label": "mockSink", "file_type": "code", "source_file": "pkg/comm/sink/decorators_test.go", "source_location": "L10"}, {"id": "sink", "label": "Sink", "file_type": "code", "source_file": "", "source_location": "", "origin_file": "/Users/gsoultan/GolandProjects/Hermod/pkg/comm/sink/decorators_test.go"}, {"id": "sink_mocksink_discoverdatabases", "label": ".DiscoverDatabases()", "file_type": "code", "source_file": "pkg/comm/sink/decorators_test.go", "source_location": "L14"}, {"id": "context", "label": "Context", "file_type": "code", "source_file": "", "source_location": "", "origin_file": "/Users/gsoultan/GolandProjects/Hermod/pkg/comm/sink/decorators_test.go"}, {"id": "sink_mocksink_discovertables", "label": ".DiscoverTables()", "file_type": "code", "source_file": "pkg/comm/sink/decorators_test.go", "source_location": "L18"}, {"id": "sink_mocksink_discovercolumns", "label": ".DiscoverColumns()", "file_type": "code", "source_file": "pkg/comm/sink/decorators_test.go", "source_location": "L22"}, {"id": "columninfo", "label": "ColumnInfo", "file_type": "code", "source_file": "", "source_location": "", "origin_file": "/Users/gsoultan/GolandProjects/Hermod/pkg/comm/sink/decorators_test.go"}, {"id": "users_gsoultan_golandprojects_hermod_pkg_comm_sink_decorators_test_testdecorators_discovery", "label": "TestDecorators_Discovery()", "file_type": "code", "source_file": "pkg/comm/sink/decorators_test.go", "source_location": "L26"}, {"id": "t", "label": "T", "file_type": "code", "source_file": "", "source_location": "", "origin_file": "/Users/gsoultan/GolandProjects/Hermod/pkg/comm/sink/decorators_test.go"}], "edges": [{"source": "users_gsoultan_golandprojects_hermod_pkg_comm_sink_decorators_test_go", "target": "go_pkg_context", "relation": "imports_from", "confidence": "EXTRACTED", "source_file": "pkg/comm/sink/decorators_test.go", "source_location": "L4", "weight": 1.0, "context": "import"}, {"source": "users_gsoultan_golandprojects_hermod_pkg_comm_sink_decorators_test_go", "target": "go_pkg_testing", "relation": "imports_from", "confidence": "EXTRACTED", "source_file": "pkg/comm/sink/decorators_test.go", "source_location": "L5", "weight": 1.0, "context": "import"}, {"source": "users_gsoultan_golandprojects_hermod_pkg_comm_sink_decorators_test_go", "target": "go_pkg_github_com_user_hermod", "relation": "imports_from", "confidence": "EXTRACTED", "source_file": "pkg/comm/sink/decorators_test.go", "source_location": "L7", "weight": 1.0, "context": "import"}, {"source": "users_gsoultan_golandprojects_hermod_pkg_comm_sink_decorators_test_go", "target": "sink_mocksink", "relation": "contains", "confidence": "EXTRACTED", "source_file": "pkg/comm/sink/decorators_test.go", "source_location": "L10", "weight": 1.0}, {"source": "sink_mocksink", "target": "sink", "relation": "embeds", "confidence": "EXTRACTED", "source_file": "pkg/comm/sink/decorators_test.go", "source_location": "L11", "weight": 1.0}, {"source": "sink_mocksink", "target": "sink_mocksink_discoverdatabases", "relation": "method", "confidence": "EXTRACTED", "source_file": "pkg/comm/sink/decorators_test.go", "source_location": "L14", "weight": 1.0}, {"source": "sink_mocksink_discoverdatabases", "target": "context", "relation": "references", "confidence": "EXTRACTED", "source_file": "pkg/comm/sink/decorators_test.go", "source_location": "L14", "weight": 1.0, "context": "parameter_type"}, {"source": "sink_mocksink", "target": "sink_mocksink_discovertables", "relation": "method", "confidence": "EXTRACTED", "source_file": "pkg/comm/sink/decorators_test.go", "source_location": "L18", "weight": 1.0}, {"source": "sink_mocksink_discovertables", "target": "context", "relation": "references", "confidence": "EXTRACTED", "source_file": "pkg/comm/sink/decorators_test.go", "source_location": "L18", "weight": 1.0, "context": "parameter_type"}, {"source": "sink_mocksink", "target": "sink_mocksink_discovercolumns", "relation": "method", "confidence": "EXTRACTED", "source_file": "pkg/comm/sink/decorators_test.go", "source_location": "L22", "weight": 1.0}, {"source": "sink_mocksink_discovercolumns", "target": "context", "relation": "references", "confidence": "EXTRACTED", "source_file": "pkg/comm/sink/decorators_test.go", "source_location": "L22", "weight": 1.0, "context": "parameter_type"}, {"source": "sink_mocksink_discovercolumns", "target": "columninfo", "relation": "references", "confidence": "EXTRACTED", "source_file": "pkg/comm/sink/decorators_test.go", "source_location": "L22", "weight": 1.0, "context": "return_type"}, {"source": "users_gsoultan_golandprojects_hermod_pkg_comm_sink_decorators_test_go", "target": "users_gsoultan_golandprojects_hermod_pkg_comm_sink_decorators_test_testdecorators_discovery", "relation": "contains", "confidence": "EXTRACTED", "source_file": "pkg/comm/sink/decorators_test.go", "source_location": "L26", "weight": 1.0}, {"source": "users_gsoultan_golandprojects_hermod_pkg_comm_sink_decorators_test_testdecorators_discovery", "target": "t", "relation": "references", "confidence": "EXTRACTED", "source_file": "pkg/comm/sink/decorators_test.go", "source_location": "L26", "weight": 1.0, "context": "parameter_type"}, {"source": "users_gsoultan_golandprojects_hermod_pkg_comm_sink_decorators_test_testdecorators_discovery", "target": "sink_mocksink_discoverdatabases", "relation": "calls", "context": "call", "confidence": "EXTRACTED", "source_file": "pkg/comm/sink/decorators_test.go", "source_location": "L37", "weight": 1.0}, {"source": "users_gsoultan_golandprojects_hermod_pkg_comm_sink_decorators_test_testdecorators_discovery", "target": "sink_mocksink_discovercolumns", "relation": "calls", "context": "call", "confidence": "EXTRACTED", "source_file": "pkg/comm/sink/decorators_test.go", "source_location": "L47", "weight": 1.0}], "raw_calls": [{"caller_nid": "users_gsoultan_golandprojects_hermod_pkg_comm_sink_decorators_test_testdecorators_discovery", "callee": "Run", "is_member_call": true, "source_file": "pkg/comm/sink/decorators_test.go", "source_location": "L29"}, {"caller_nid": "users_gsoultan_golandprojects_hermod_pkg_comm_sink_decorators_test_testdecorators_discovery", "callee": "NewTracingSink", "is_member_call": false, "source_file": "pkg/comm/sink/decorators_test.go", "source_location": "L30"}, {"caller_nid": "users_gsoultan_golandprojects_hermod_pkg_comm_sink_decorators_test_testdecorators_discovery", "callee": "Fatal", "is_member_call": true, "source_file": "pkg/comm/sink/decorators_test.go", "source_location": "L34"}, {"caller_nid": "users_gsoultan_golandprojects_hermod_pkg_comm_sink_decorators_test_testdecorators_discovery", "callee": "Background", "is_member_call": false, "source_file": "pkg/comm/sink/decorators_test.go", "source_location": "L37"}, {"caller_nid": "users_gsoultan_golandprojects_hermod_pkg_comm_sink_decorators_test_testdecorators_discovery", "callee": "Errorf", "is_member_call": true, "source_file": "pkg/comm/sink/decorators_test.go", "source_location": "L39"}, {"caller_nid": "users_gsoultan_golandprojects_hermod_pkg_comm_sink_decorators_test_testdecorators_discovery", "callee": "Fatal", "is_member_call": true, "source_file": "pkg/comm/sink/decorators_test.go", "source_location": "L44"}, {"caller_nid": "users_gsoultan_golandprojects_hermod_pkg_comm_sink_decorators_test_testdecorators_discovery", "callee": "Background", "is_member_call": false, "source_file": "pkg/comm/sink/decorators_test.go", "source_location": "L47"}, {"caller_nid": "users_gsoultan_golandprojects_hermod_pkg_comm_sink_decorators_test_testdecorators_discovery", "callee": "Errorf", "is_member_call": true, "source_file": "pkg/comm/sink/decorators_test.go", "source_location": "L49"}, {"caller_nid": "users_gsoultan_golandprojects_hermod_pkg_comm_sink_decorators_test_testdecorators_discovery", "callee": "Run", "is_member_call": true, "source_file": "pkg/comm/sink/decorators_test.go", "source_location": "L53"}, {"caller_nid": "users_gsoultan_golandprojects_hermod_pkg_comm_sink_decorators_test_testdecorators_discovery", "callee": "NewRetrySink", "is_member_call": false, "source_file": "pkg/comm/sink/decorators_test.go", "source_location": "L54"}, {"caller_nid": "users_gsoultan_golandprojects_hermod_pkg_comm_sink_decorators_test_testdecorators_discovery", "callee": "Fatal", "is_member_call": true, "source_file": "pkg/comm/sink/decorators_test.go", "source_location": "L58"}, {"caller_nid": "users_gsoultan_golandprojects_hermod_pkg_comm_sink_decorators_test_testdecorators_discovery", "callee": "Background", "is_member_call": false, "source_file": "pkg/comm/sink/decorators_test.go", "source_location": "L61"}, {"caller_nid": "users_gsoultan_golandprojects_hermod_pkg_comm_sink_decorators_test_testdecorators_discovery", "callee": "Errorf", "is_member_call": true, "source_file": "pkg/comm/sink/decorators_test.go", "source_location": "L63"}]}